LICENSE
MANIFEST.in
README.rst
requirements.txt
setup.cfg
setup.py
OpenPGPyCard/OpenPGPCard.py
OpenPGPyCard/__init__.py
OpenPGPyCard.egg-info/PKG-INFO
OpenPGPyCard.egg-info/SOURCES.txt
OpenPGPyCard.egg-info/dependency_links.txt
OpenPGPyCard.egg-info/requires.txt
OpenPGPyCard.egg-info/top_level.txt