Metadata-Version: 1.1
Name: OpenPGPyCard
Version: 0.0.1.dev2
Summary: OpenPGPyCard is a simple OpenPGP card driver.
Home-page: https://github.com/mark-in/OpenPGPyCard
Author: Ivan Markin
Author-email: mark-in@users.noreply.github.com
License: GPL
Keywords: openpgp,card,smartcard
Platform: UNKNOWN
Classifier: Development Status :: 3 - Alpha
Classifier: License :: OSI Approved :: GNU General Public License (GPL)
Classifier: Programming Language :: Python :: 2
Classifier: Programming Language :: Python :: 2.7
Classifier: Programming Language :: Python :: 3
Classifier: Programming Language :: Python :: 3.3
